rutube_cold_start/__about__.py
rutube_cold_start/__init__.py
rutube_cold_start/config.py
rutube_cold_start/main.py
rutube_cold_start/recommender.py
rutube_cold_start-1.3.1.dist-info/METADATA
rutube_cold_start-1.3.1.dist-info/WHEEL
rutube_cold_start-1.3.1.dist-info/licenses/LICENSE
rutube_cold_start-1.3.1.dist-info/RECORD
